jupyterlab_rise/__init__.py
jupyterlab_rise/__main__.py
jupyterlab_rise/_version.py
jupyterlab_rise/app.py
jupyterlab_rise/serverextension.py
jupyterlab_rise/schemas/@jupyterlab/application-extension/commands.json
jupyterlab_rise/schemas/@jupyterlab/application-extension/context-menu.json
jupyterlab_rise/schemas/@jupyterlab/application-extension/package.json.orig
jupyterlab_rise/schemas/@jupyterlab/application-extension/property-inspector.json
jupyterlab_rise/schemas/@jupyterlab/application-extension/shell.json
jupyterlab_rise/schemas/@jupyterlab/application-extension/top-bar.json
jupyterlab_rise/schemas/@jupyterlab/apputils-extension/notification.json
jupyterlab_rise/schemas/@jupyterlab/apputils-extension/package.json.orig
jupyterlab_rise/schemas/@jupyterlab/apputils-extension/palette.json
jupyterlab_rise/schemas/@jupyterlab/apputils-extension/print.json
jupyterlab_rise/schemas/@jupyterlab/apputils-extension/sanitizer.json
jupyterlab_rise/schemas/@jupyterlab/apputils-extension/themes.json
jupyterlab_rise/schemas/@jupyterlab/apputils-extension/utilityCommands.json
jupyterlab_rise/schemas/@jupyterlab/apputils-extension/workspaces.json
jupyterlab_rise/schemas/@jupyterlab/codemirror-extension/package.json.orig
jupyterlab_rise/schemas/@jupyterlab/codemirror-extension/plugin.json
jupyterlab_rise/schemas/@jupyterlab/docmanager-extension/download.json
jupyterlab_rise/schemas/@jupyterlab/docmanager-extension/package.json.orig
jupyterlab_rise/schemas/@jupyterlab/docmanager-extension/plugin.json
jupyterlab_rise/schemas/@jupyterlab/mathjax-extension/package.json.orig
jupyterlab_rise/schemas/@jupyterlab/mathjax-extension/plugin.json
jupyterlab_rise/schemas/@jupyterlab/notebook-extension/completer.json
jupyterlab_rise/schemas/@jupyterlab/notebook-extension/export.json
jupyterlab_rise/schemas/@jupyterlab/notebook-extension/package.json.orig
jupyterlab_rise/schemas/@jupyterlab/notebook-extension/panel.json
jupyterlab_rise/schemas/@jupyterlab/notebook-extension/tools.json
jupyterlab_rise-0.42.0.dist-info/METADATA
jupyterlab_rise-0.42.0.dist-info/WHEEL
jupyterlab_rise-0.42.0.dist-info/licenses/LICENSE
jupyterlab_rise-0.42.0.dist-info/RECORD
